MANIFEST.in
requirements.txt
setup.cfg
setup.py
sklearn_stub.egg-info/PKG-INFO
sklearn_stub.egg-info/SOURCES.txt
sklearn_stub.egg-info/dependency_links.txt
sklearn_stub.egg-info/requires.txt
sklearn_stub.egg-info/top_level.txt
sklstub/__init__.py
sklstub/stub.py